zyphra/__init__.py
zyphra/client.py
zyphra/models/__init__.py
zyphra/models/audio.py
zyphra/models/base.py
zyphra/models/chat.py
zyphra-0.1.6.dist-info/METADATA
zyphra-0.1.6.dist-info/WHEEL
zyphra-0.1.6.dist-info/top_level.txt
zyphra-0.1.6.dist-info/RECORD
