Metadata-Version: 2.4
Name: zyphra
Version: 0.1.6
Summary: Python client for Zyphra APIs
Author-email: Ian Sears <ian@zyphra.com>
Project-URL: Homepage, https://www.zyphra.com/
Requires-Python: >=3.8
Requires-Dist: aiohttp>=3.8.0
Requires-Dist: pydantic>=2.0.0
Requires-Dist: requests>=2.25.0
Provides-Extra: dev
Requires-Dist: pytest>=7.0; extra == "dev"
Requires-Dist: pytest-asyncio>=0.21.0; extra == "dev"
Requires-Dist: black>=23.0; extra == "dev"
Requires-Dist: mypy>=1.0; extra == "dev"
Requires-Dist: aioresponses>=0.8.0; extra == "dev"
